[
  {
    "timestamp": "2026-05-04T00:00:00Z",
    "country": "USA",
    "lat": 40.7128,
    "lon": -74.006,
    "risk_score": 43,
    "title": "ACLED Event: Protests",
    "source_url": "ACLED Placeholder Data",
    "tag": "conflict"
  },
  {
    "timestamp": "2026-05-06T04:11:19.904444Z",
    "country": "GL",
    "lat": null,
    "lon": null,
    "risk_score": 39,
    "title": "Markets digest bank earnings after recent turmoil",
    "source_url": "https://www.cnn.com/business/live-news/stock-market-bank-earnings/index.html",
    "tag": "news"
  },
  {
    "timestamp": "2026-05-06T04:11:19.904444Z",
    "country": "GL",
    "lat": null,
    "lon": null,
    "risk_score": 38,
    "title": "Still haven't filed your taxes? Here's what you need to know",
    "source_url": "https://www.cnn.com/2023/04/13/success/tax-filing-tips/index.html",
    "tag": "news"
  },
  {
    "timestamp": "2026-05-06T04:11:19.904444Z",
    "country": "GL",
    "lat": null,
    "lon": null,
    "risk_score": 43,
    "title": "Retail spending fell in March as consumers pull back",
    "source_url": "https://www.cnn.com/2023/04/14/economy/march-retail-sales/index.html",
    "tag": "news"
  },
  {
    "timestamp": "2026-05-06T04:11:19.904444Z",
    "country": "GL",
    "lat": null,
    "lon": null,
    "risk_score": 26,
    "title": "Analysis: Fox News is about to enter the true No Spin Zone",
    "source_url": "https://www.cnn.com/2023/04/14/media/fox-news-dominion-hnk-intl/index.html",
    "tag": "news"
  },
  {
    "timestamp": "2026-05-06T04:11:19.904444Z",
    "country": "GL",
    "lat": null,
    "lon": null,
    "risk_score": 23,
    "title": "Silicon Valley Bank collapse renews calls to address disparities impacting entrepreneurs of color",
    "source_url": "https://www.cnn.com/2023/04/13/business/silicon-valley-bank-entrepreneurs-of-color-reaj/index.html",
    "tag": "news"
  },
  {
    "timestamp": "2026-05-06T04:11:19.904444Z",
    "country": "GL",
    "lat": null,
    "lon": null,
    "risk_score": 22,
    "title": "Not only is Lake Powell's water level plummeting because of drought, its total capacity is shrinking, too",
    "source_url": "https://www.cnn.com/2022/03/21/us/lake-powell-capacity-shrinking-drought-climate/index.html",
    "tag": "news"
  },
  {
    "timestamp": "2026-05-06T04:11:19.904444Z",
    "country": "GL",
    "lat": null,
    "lon": null,
    "risk_score": 44,
    "title": "These were the best and worst places for air quality in 2021, new report shows",
    "source_url": "https://www.cnn.com/2022/03/22/world/air-pollution-2021-iqair-report-climate/index.html",
    "tag": "news"
  },
  {
    "timestamp": "2026-05-06T04:11:19.904444Z",
    "country": "GL",
    "lat": null,
    "lon": null,
    "risk_score": 46,
    "title": "Big-box stores could help slash emissions and save millions by putting solar panels on roofs. Why aren't more of them doing it?",
    "source_url": "https://www.cnn.com/2022/03/20/us/solar-power-on-big-box-store-rooftops-climate/index.html",
    "tag": "news"
  },
  {
    "timestamp": "2026-05-06T04:11:19.904444Z",
    "country": "GL",
    "lat": null,
    "lon": null,
    "risk_score": 39,
    "title": "Look of the Week: Blackpink headline Coachella in Korean hanboks",
    "source_url": "https://www.cnn.com/style/article/blackpink-coachella-2023-hanboks-lotw/index.html",
    "tag": "news"
  },
  {
    "timestamp": "2026-05-06T04:11:19.904444Z",
    "country": "GL",
    "lat": null,
    "lon": null,
    "risk_score": 31,
    "title": "Scientists identify secret ingredient in Leonardo da Vinci paintings",
    "source_url": "https://www.cnn.com/style/article/old-masters-da-vinci-egg-yolk-painting-scn/index.html",
    "tag": "news"
  },
  {
    "timestamp": "2026-05-06T04:11:19.904444Z",
    "country": "GL",
    "lat": null,
    "lon": null,
    "risk_score": 44,
    "title": "How Playboy cut ties with Hugh Hefner to create a post-MeToo brand",
    "source_url": "https://www.cnn.com/style/article/playboy-the-conversation/index.html",
    "tag": "news"
  },
  {
    "timestamp": "2026-05-06T04:11:19.904444Z",
    "country": "GL",
    "lat": null,
    "lon": null,
    "risk_score": 49,
    "title": "'A definitive backslide.' Inside fashion's worrying runway trend",
    "source_url": "https://www.cnn.com/style/article/fashion-week-fall-winter-2023-size-diversity-skinny-wegovy/index.html",
    "tag": "news"
  },
  {
    "timestamp": "2026-05-06T04:11:19.904444Z",
    "country": "GL",
    "lat": null,
    "lon": null,
    "risk_score": 23,
    "title": "Michael Jordan's 1998 NBA Finals sneakers sell for a record $2.2 million",
    "source_url": "https://www.cnn.com/style/article/michael-jordan-sneakers-1998-finals-sothebys-auction-record/index.html",
    "tag": "news"
  },
  {
    "timestamp": "2026-05-06T04:11:19.904444Z",
    "country": "GL",
    "lat": null,
    "lon": null,
    "risk_score": 41,
    "title": "The surreal facades of America's strip clubs",
    "source_url": "https://www.cnn.com/style/article/francois-prost-gentlemens-club/index.html",
    "tag": "news"
  },
  {
    "timestamp": "2026-05-06T04:11:19.904444Z",
    "country": "GL",
    "lat": null,
    "lon": null,
    "risk_score": 43,
    "title": "Here's the real reason to turn on airplane mode when you fly",
    "source_url": "https://www.cnn.com/travel/article/airplane-mode-reasons-why/index.html",
    "tag": "news"
  },
  {
    "timestamp": "2026-05-06T04:11:19.904444Z",
    "country": "GL",
    "lat": null,
    "lon": null,
    "risk_score": 29,
    "title": "'I was up to my waist down a hippo's throat.' He survived, and here's his advice",
    "source_url": "https://www.cnn.com/travel/article/hippo-attack-avoid-survive-paul-templer/index.html",
    "tag": "news"
  },
  {
    "timestamp": "2026-05-06T04:11:19.904444Z",
    "country": "GL",
    "lat": null,
    "lon": null,
    "risk_score": 42,
    "title": "They bought an abandoned 'ghost house' in the Japanese countryside",
    "source_url": "https://www.cnn.com/travel/article/couple-turned-abandoned-japanese-home-into-guest-house/index.html",
    "tag": "news"
  },
  {
    "timestamp": "2026-05-06T04:11:19.904444Z",
    "country": "GL",
    "lat": null,
    "lon": null,
    "risk_score": 19,
    "title": "Relaxed entry rules make it easier than ever to visit this stunning Asian nation",
    "source_url": "https://www.cnn.com/travel/article/mongolia-reasons-to-visit-2023/index.html",
    "tag": "news"
  },
  {
    "timestamp": "2026-05-06T04:11:19.904444Z",
    "country": "GL",
    "lat": null,
    "lon": null,
    "risk_score": 50,
    "title": "The most beautiful sections of China's Great Wall",
    "source_url": "https://www.cnn.com/travel/article/china-beautiful-great-wall-sections-cmd/index.html",
    "tag": "news"
  },
  {
    "timestamp": "2026-05-06T04:11:19.904444Z",
    "country": "GL",
    "lat": null,
    "lon": null,
    "risk_score": 51,
    "title": "Sign up to our newsletter for a weekly roundup of travel news",
    "source_url": "https://www.cnn.com/specials/travel-newsletter",
    "tag": "news"
  },
  {
    "timestamp": "2026-05-06T04:11:19.904444Z",
    "country": "GL",
    "lat": null,
    "lon": null,
    "risk_score": 19,
    "title": "Nelly Cheboi, who creates computer labs for Kenyan schoolchildren, is CNN's Hero of the Year",
    "source_url": "https://www.cnn.com/2022/12/11/us/cnn-heroes-all-star-tribute-hero-of-the-year/index.html",
    "tag": "news"
  },
  {
    "timestamp": "2026-05-06T04:11:19.904444Z",
    "country": "GL",
    "lat": null,
    "lon": null,
    "risk_score": 50,
    "title": "CNN Heroes: Sharing the Spotlight",
    "source_url": "https://www.cnn.com/specials/cnn-heroes-salutes-special",
    "tag": "news"
  },
  {
    "timestamp": "2026-05-06T04:11:19.904444Z",
    "country": "GL",
    "lat": null,
    "lon": null,
    "risk_score": 42,
    "title": "Donate now to a Top 10 CNN Hero",
    "source_url": "https://www.cnn.com/videos/tv/2021/11/26/how-to-donate-matching-cnnheroes.cnn",
    "tag": "news"
  },
  {
    "timestamp": "2026-05-06T04:11:19.904444Z",
    "country": "GL",
    "lat": null,
    "lon": null,
    "risk_score": 21,
    "title": "0% intro APR until 2024 is 100% insane",
    "source_url": "https://www.fool.com/the-ascent/credit-cards/landing/wells-fargo-reflect-review/?utm_site=theascent&utm_campaign=ta-cc-co-cnn-welref2-ron-5-hp-sfpb&utm_medium=cpc&utm_source=cnn",
    "tag": "news"
  },
  {
    "timestamp": "2026-05-06T04:11:19.904444Z",
    "country": "GL",
    "lat": null,
    "lon": null,
    "risk_score": 43,
    "title": "It's official: now avoid credit card interest into 2024",
    "source_url": "https://www.fool.com/the-ascent/credit-cards/landing/citi-simplicity-review/?utm_site=theascent&utm_campaign=ta-cc-co-cnn-citisimp2-ron-5-hp-sfpb&utm_medium=cpc&utm_source=cnn",
    "tag": "news"
  },
  {
    "timestamp": "2026-05-06T04:11:19.904444Z",
    "country": "GL",
    "lat": null,
    "lon": null,
    "risk_score": 33,
    "title": "Experts: this is the best cash back card of 2022",
    "source_url": "https://www.fool.com/the-ascent/credit-cards/landing/wells-fargo-active-cash-card-review/?utm_site=theascent&utm_campaign=ta-cc-co-cnn-welac2-ron-5-hp-sfpb&utm_medium=cpc&utm_source=cnn",
    "tag": "news"
  },
  {
    "timestamp": "2026-05-06T04:11:19.904444Z",
    "country": "GL",
    "lat": null,
    "lon": null,
    "risk_score": 38,
    "title": "Turn Your Rising Home Equity Into Cash You Can Use",
    "source_url": "https://www.lendingtree.com/?splitterid=home-equity&cproduct=he&cchannel=content&csource=cnn&cmethod=heform&ccreative=risingequitycash_housemoneystack&placement_name=sectionfronts&ad_headline=risingequitycash&ad_image_name=housemoneystack&ctype=sectionfronts&bdst=revshare&mtaid=AC53E&esourceid=6348616",
    "tag": "news"
  },
  {
    "timestamp": "2026-05-06T04:11:19.904444Z",
    "country": "GL",
    "lat": null,
    "lon": null,
    "risk_score": 34,
    "title": "Dream Big with a Home Equity Loan",
    "source_url": "https://www.lendingtree.com/?splitterid=home-equity&cproduct=he&cchannel=content&csource=cnn&cmethod=heform&ccreative=dreambighomeequity_housemoneystack&placement_name=sectionfronts&ad_headline=dreambighomeequity&ad_image_name=housemoneystack&ctype=sectionfronts&bdst=revshare&mtaid=AC53E&esourceid=6348616",
    "tag": "news"
  },
  {
    "timestamp": "2026-05-06T04:11:19.904444Z",
    "country": "GL",
    "lat": null,
    "lon": null,
    "risk_score": 40,
    "title": "Want Cash Out of Your Home? Here Are Your Best Options",
    "source_url": "https://www.lendingtree.com/?splitterid=home-equity&cproduct=he&cchannel=content&csource=cnn&cmethod=heform&ccreative=cashoutoptions_housemoneystack&placement_name=sectionfronts&ad_headline=cashoutoptions&ad_image_name=housemoneystack&ctype=sectionfronts&bdst=revshare&mtaid=AC53E&esourceid=6348616",
    "tag": "news"
  },
  {
    "timestamp": "2026-05-06T04:11:19.904444Z",
    "country": "GL",
    "lat": null,
    "lon": null,
    "risk_score": 34,
    "title": "Trump says US to pause operation to guide vessels through Strait of Hormuz",
    "source_url": "https://www.bbc.com/news/articles/clypekl71gdo?at_medium=RSS&at_campaign=rss",
    "tag": "news"
  },
  {
    "timestamp": "2026-05-06T04:11:19.904444Z",
    "country": "GL",
    "lat": null,
    "lon": null,
    "risk_score": 50,
    "title": "Hantavirus may have spread between passengers on cruise ship, WHO says",
    "source_url": "https://www.bbc.com/news/articles/cm2p186gyp2o?at_medium=RSS&at_campaign=rss",
    "tag": "news"
  },
  {
    "timestamp": "2026-05-06T04:11:19.904444Z",
    "country": "GL",
    "lat": null,
    "lon": null,
    "risk_score": 50,
    "title": "Vivek Ramaswamy wins Republican nomination for Ohio governor",
    "source_url": "https://www.bbc.com/news/articles/c4g0xe4qlzxo?at_medium=RSS&at_campaign=rss",
    "tag": "news"
  },
  {
    "timestamp": "2026-05-06T04:11:19.904444Z",
    "country": "GL",
    "lat": null,
    "lon": null,
    "risk_score": 23,
    "title": "Russian attacks kill more than 20 ahead of rival ceasefires proposed by Kyiv and Moscow",
    "source_url": "https://www.bbc.com/news/articles/c1e2zjz22p9o?at_medium=RSS&at_campaign=rss",
    "tag": "news"
  },
  {
    "timestamp": "2026-05-06T04:11:19.904444Z",
    "country": "GL",
    "lat": null,
    "lon": null,
    "risk_score": 23,
    "title": "Nine coal miners die in gas explosion in Colombia",
    "source_url": "https://www.bbc.com/news/articles/cdxpe02y05go?at_medium=RSS&at_campaign=rss",
    "tag": "news"
  },
  {
    "timestamp": "2026-05-06T04:11:19.904444Z",
    "country": "GL",
    "lat": null,
    "lon": null,
    "risk_score": 20,
    "title": "Two killed and many injured after car driven into crowd in German city of Leipzig",
    "source_url": "https://www.bbc.com/news/articles/ckgpzgxgz58o?at_medium=RSS&at_campaign=rss",
    "tag": "news"
  },
  {
    "timestamp": "2026-05-06T04:11:19.904444Z",
    "country": "GL",
    "lat": null,
    "lon": null,
    "risk_score": 22,
    "title": "Romanian PM ousted in no-confidence vote",
    "source_url": "https://www.bbc.com/news/articles/cgkpjz2638ro?at_medium=RSS&at_campaign=rss",
    "tag": "news"
  },
  {
    "timestamp": "2026-05-06T04:11:19.904444Z",
    "country": "GL",
    "lat": null,
    "lon": null,
    "risk_score": 52,
    "title": "Oil prices ease as US pauses Project Freedom to seek deal with Iran",
    "source_url": "https://www.bbc.com/news/articles/c4g8zejyyr3o?at_medium=RSS&at_campaign=rss",
    "tag": "news"
  },
  {
    "timestamp": "2026-05-06T04:11:19.904444Z",
    "country": "GL",
    "lat": null,
    "lon": null,
    "risk_score": 39,
    "title": "Apple to pay $250m to US iPhone buyers over AI features lawsuit",
    "source_url": "https://www.bbc.com/news/articles/c0j2nydnzy7o?at_medium=RSS&at_campaign=rss",
    "tag": "news"
  },
  {
    "timestamp": "2026-05-06T04:11:19.904444Z",
    "country": "GL",
    "lat": null,
    "lon": null,
    "risk_score": 49,
    "title": "A 'fun' superstar stuns rivals and reshapes politics in an Indian state",
    "source_url": "https://www.bbc.com/news/articles/c8xwjx54zggo?at_medium=RSS&at_campaign=rss",
    "tag": "news"
  },
  {
    "timestamp": "2026-05-06T04:11:19.904444Z",
    "country": "GL",
    "lat": null,
    "lon": null,
    "risk_score": 39,
    "title": "Popular Australian author pleads guilty over child exploitation material",
    "source_url": "https://www.bbc.com/news/articles/cg7pz2xj4l3o?at_medium=RSS&at_campaign=rss",
    "tag": "news"
  },
  {
    "timestamp": "2026-05-06T04:11:19.904444Z",
    "country": "GL",
    "lat": null,
    "lon": null,
    "risk_score": 35,
    "title": "Rescuers among three dead after yacht sinks off Australian coast",
    "source_url": "https://www.bbc.com/news/articles/cr5p36v5q79o?at_medium=RSS&at_campaign=rss",
    "tag": "news"
  },
  {
    "timestamp": "2026-05-06T04:11:19.904444Z",
    "country": "GL",
    "lat": null,
    "lon": null,
    "risk_score": 24,
    "title": "Explosion at China fireworks factory kills 26 people",
    "source_url": "https://www.bbc.com/news/articles/c70vqwengxno?at_medium=RSS&at_campaign=rss",
    "tag": "news"
  },
  {
    "timestamp": "2026-05-06T04:11:19.904444Z",
    "country": "GL",
    "lat": null,
    "lon": null,
    "risk_score": 41,
    "title": "Deadly China plane crash was caused by fuel cut-off, says report",
    "source_url": "https://www.bbc.com/news/articles/ckgpy223y9go?at_medium=RSS&at_campaign=rss",
    "tag": "news"
  },
  {
    "timestamp": "2026-05-06T04:11:19.904444Z",
    "country": "GL",
    "lat": null,
    "lon": null,
    "risk_score": 35,
    "title": "Rapper Kid Cudi removes British star M.I.A. from tour",
    "source_url": "https://www.bbc.com/news/articles/ceqp9y71nq2o?at_medium=RSS&at_campaign=rss",
    "tag": "news"
  },
  {
    "timestamp": "2026-05-06T04:11:19.904444Z",
    "country": "GL",
    "lat": null,
    "lon": null,
    "risk_score": 38,
    "title": "Ukrainian drone hits upmarket Moscow high-rise ahead of Victory Day celebrations",
    "source_url": "https://www.bbc.com/news/articles/cwy234llx3vo?at_medium=RSS&at_campaign=rss",
    "tag": "news"
  },
  {
    "timestamp": "2026-05-06T04:11:19.904444Z",
    "country": "GL",
    "lat": null,
    "lon": null,
    "risk_score": 36,
    "title": "Three Russian diplomats expelled from Austria over spying accusations",
    "source_url": "https://www.bbc.com/news/articles/c5yrwny111xo?at_medium=RSS&at_campaign=rss",
    "tag": "news"
  },
  {
    "timestamp": "2026-05-06T04:11:19.904444Z",
    "country": "GL",
    "lat": null,
    "lon": null,
    "risk_score": 25,
    "title": "Mali junta leader names himself defence minister after predecessor killed",
    "source_url": "https://www.bbc.com/news/articles/c8r8jr7x8mlo?at_medium=RSS&at_campaign=rss",
    "tag": "news"
  },
  {
    "timestamp": "2026-05-06T04:11:19.904444Z",
    "country": "GL",
    "lat": null,
    "lon": null,
    "risk_score": 45,
    "title": "Britney Spears pleads guilty to reckless driving after arrest",
    "source_url": "https://www.bbc.com/news/articles/ce9p09e5vnro?at_medium=RSS&at_campaign=rss",
    "tag": "news"
  },
  {
    "timestamp": "2026-05-06T04:11:19.904444Z",
    "country": "GL",
    "lat": null,
    "lon": null,
    "risk_score": 25,
    "title": "Former New York City mayor Rudy Giuliani recovering from pneumonia and 'now breathing on his own'",
    "source_url": "https://www.bbc.com/news/articles/cpvpnve1r24o?at_medium=RSS&at_campaign=rss",
    "tag": "news"
  },
  {
    "timestamp": "2026-05-06T04:11:19.904444Z",
    "country": "GL",
    "lat": null,
    "lon": null,
    "risk_score": 27,
    "title": "The most talked-about looks at this year's Met Gala",
    "source_url": "https://www.bbc.com/news/articles/c5y9wq9y0p1o?at_medium=RSS&at_campaign=rss",
    "tag": "news"
  },
  {
    "timestamp": "2026-05-06T04:11:19.904444Z",
    "country": "GL",
    "lat": null,
    "lon": null,
    "risk_score": 26,
    "title": "India's fiercest female politician faces a fight for survival",
    "source_url": "https://www.bbc.com/news/articles/c202p14qwr5o?at_medium=RSS&at_campaign=rss",
    "tag": "news"
  },
  {
    "timestamp": "2026-05-06T04:11:19.904444Z",
    "country": "GL",
    "lat": null,
    "lon": null,
    "risk_score": 49,
    "title": "Finding soldier Tom: Solving family mystery of WW2 Soviet prisoner of war",
    "source_url": "https://www.bbc.com/news/articles/cdjpdzvzy41o?at_medium=RSS&at_campaign=rss",
    "tag": "news"
  },
  {
    "timestamp": "2026-05-06T04:11:19.904444Z",
    "country": "GL",
    "lat": null,
    "lon": null,
    "risk_score": 26,
    "title": "Robots move in as waste firms struggle to find staff",
    "source_url": "https://www.bbc.com/news/articles/cvg0w84q1wyo?at_medium=RSS&at_campaign=rss",
    "tag": "news"
  },
  {
    "timestamp": "2026-05-06T04:11:19.904444Z",
    "country": "GL",
    "lat": null,
    "lon": null,
    "risk_score": 22,
    "title": "Kenya battles to stop the 'goons and guns' as fears of political violence grow",
    "source_url": "https://www.bbc.com/news/articles/c9qdz0p0x5qo?at_medium=RSS&at_campaign=rss",
    "tag": "news"
  },
  {
    "timestamp": "2026-05-06T04:11:19.904444Z",
    "country": "GL",
    "lat": null,
    "lon": null,
    "risk_score": 32,
    "title": "Voters will judge Trump on the economy - how is it doing?",
    "source_url": "https://www.bbc.com/news/articles/cgepyv20vrpo?at_medium=RSS&at_campaign=rss",
    "tag": "news"
  },
  {
    "timestamp": "2026-05-06T04:11:19.904444Z",
    "country": "GL",
    "lat": null,
    "lon": null,
    "risk_score": 33,
    "title": "Laufey on making jazz cool again (and the fish that brought out her inner rage)",
    "source_url": "https://www.bbc.com/news/articles/c99lvggdy4jo?at_medium=RSS&at_campaign=rss",
    "tag": "news"
  },
  {
    "timestamp": "2026-05-06T04:11:19.904444Z",
    "country": "GL",
    "lat": null,
    "lon": null,
    "risk_score": 22,
    "title": "Do viruses spread more easily on cruise ships?",
    "source_url": "https://www.bbc.com/news/videos/cdxpn5r2nlgo?at_medium=RSS&at_campaign=rss",
    "tag": "news"
  },
  {
    "timestamp": "2026-05-06T04:11:19.904444Z",
    "country": "GL",
    "lat": null,
    "lon": null,
    "risk_score": 20,
    "title": "Moment Indonesian river overflows from heavy rain",
    "source_url": "https://www.bbc.com/news/videos/ckgpyel2n0eo?at_medium=RSS&at_campaign=rss",
    "tag": "news"
  },
  {
    "timestamp": "2026-05-06T04:11:19.904444Z",
    "country": "GL",
    "lat": null,
    "lon": null,
    "risk_score": 46,
    "title": "Watch: Moment United Airlines flight strikes vehicle during landing",
    "source_url": "https://www.bbc.com/news/videos/cr7pvgl9dpeo?at_medium=RSS&at_campaign=rss",
    "tag": "news"
  },
  {
    "timestamp": "2026-05-06T04:11:19.904444Z",
    "country": "GL",
    "lat": null,
    "lon": null,
    "risk_score": 26,
    "title": "Huge crowd attends free Shakira Copacabana beach concert",
    "source_url": "https://www.bbc.com/news/videos/c8r8j50zxnno?at_medium=RSS&at_campaign=rss",
    "tag": "news"
  }
]